{
  "prepare_queue": {
    "installed": [],
    "uninstalled": []
  },
  "config_munge": {
    "files": {
      "./res/values/strings.xml": {
        "parents": {
          "/resources": [
            {
              "xml": "<string name=\"fb_app_id\">296790334414922</string>",
              "count": 13
            },
            {
              "xml": "<string name=\"fb_app_name\">Chalkbord</string>",
              "count": 13
            }
          ]
        }
      },
      "res/xml/config.xml": {
        "parents": {
          "/*": [
            {
              "xml": "<feature name=\"ActionSheet\"><param name=\"android-package\" value=\"nl.xservices.plugins.actionsheet.ActionSheet\" /></feature>",
              "count": 1
            },
            {
              "xml": "<feature name=\"Camera\"><param name=\"android-package\" value=\"org.apache.cordova.camera.CameraLauncher\" /></feature>",
              "count": 1
            },
            {
              "xml": "<feature name=\"Device\"><param name=\"android-package\" value=\"org.apache.cordova.device.Device\" /></feature>",
              "count": 1
            },
            {
              "xml": "<feature name=\"Notification\"><param name=\"android-package\" value=\"org.apache.cordova.dialogs.Notification\" /></feature>",
              "count": 1
            },
            {
              "xml": "<feature name=\"FacebookConnectPlugin\"><param name=\"android-package\" value=\"org.apache.cordova.facebook.ConnectPlugin\" /><param name=\"onload\" value=\"true\" /></feature>",
              "count": 1
            },
            {
              "xml": "<access origin=\"https://m.facebook.com\" />",
              "count": 1
            },
            {
              "xml": "<access origin=\"https://graph.facebook.com\" />",
              "count": 1
            },
            {
              "xml": "<access origin=\"https://api.facebook.com\" />",
              "count": 1
            },
            {
              "xml": "<access origin=\"https://*.fbcdn.net\" />",
              "count": 1
            },
            {
              "xml": "<access origin=\"https://*.akamaihd.net\" />",
              "count": 1
            },
            {
              "xml": "<preference name=\"android-minSdkVersion\" value=\"15\" />",
              "count": 1
            },
            {
              "xml": "<feature name=\"Geolocation\"><param name=\"android-package\" value=\"org.apache.cordova.geolocation.Geolocation\" /></feature>",
              "count": 1
            },
            {
              "xml": "<feature name=\"InAppBrowser\"><param name=\"android-package\" value=\"org.apache.cordova.inappbrowser.InAppBrowser\" /></feature>",
              "count": 1
            },
            {
              "xml": "<feature name=\"SplashScreen\"><param name=\"android-package\" value=\"org.apache.cordova.splashscreen.SplashScreen\" /><param name=\"onload\" value=\"true\" /></feature>",
              "count": 1
            },
            {
              "xml": "<feature name=\"StatusBar\"><param name=\"android-package\" value=\"org.apache.cordova.statusbar.StatusBar\" /><param name=\"onload\" value=\"true\" /></feature>",
              "count": 1
            },
            {
              "xml": "<feature name=\"UniqueDeviceID\"><param name=\"android-package\" value=\"hu.dpal.phonegap.plugins.UniqueDeviceID\" /></feature>",
              "count": 1
            },
            {
              "xml": "<feature name=\"DeviceFeedback\"><param name=\"android-package\" value=\"cz.Velda.cordova.plugin.devicefeedback.DeviceFeedback\" /><param name=\"onload\" value=\"true\" /></feature>",
              "count": 1
            },
            {
              "xml": "<feature name=\"Whitelist\"><param name=\"android-package\" value=\"org.apache.cordova.whitelist.WhitelistPlugin\" /><param name=\"onload\" value=\"true\" /></feature>",
              "count": 1
            },
            {
              "xml": "<feature name=\"SQLitePlugin\"><param name=\"android-package\" value=\"io.sqlc.SQLitePlugin\" /></feature>",
              "count": 1
            },
            {
              "xml": "<feature name=\"CallNumber\"><param name=\"android-package\" value=\"mx.ferreyra.callnumber.CFCallNumber\" /></feature>",
              "count": 1
            },
            {
              "xml": "<feature name=\"LaunchNavigator\"><param name=\"android-package\" value=\"uk.co.workingedge.phonegap.plugin.LaunchNavigator\" /></feature>",
              "count": 1
            }
          ]
        }
      },
      "AndroidManifest.xml": {
        "parents": {
          "/*": [
            {
              "xml": "<uses-permission android:name=\"android.permission.WRITE_EXTERNAL_STORAGE\" />",
              "count": 1
            },
            {
              "xml": "<uses-permission android:name=\"android.permission.ACCESS_COARSE_LOCATION\" />",
              "count": 1
            },
            {
              "xml": "<uses-permission android:name=\"android.permission.ACCESS_FINE_LOCATION\" />",
              "count": 1
            },
            {
              "xml": "<uses-feature android:name=\"android.hardware.location.gps\" />",
              "count": 1
            },
            {
              "xml": "<uses-permission android:name=\"android.permission.READ_PHONE_STATE\" />",
              "count": 1
            },
            {
              "xml": "<uses-permission android:name=\"android.permission.CALL_PHONE\" />",
              "count": 1
            },
            {
              "xml": "<uses-feature android:name=\"android.hardware.telephony\" android:required=\"false\" />",
              "count": 1
            },
            {
              "xml": "<uses-permission android:name=\"android.permission.ACCESS_NETWORK_STATE\" />",
              "count": 1
            }
          ],
          "application": [
            {
              "xml": "<provider android:authorities=\"${applicationId}.provider\" android:exported=\"false\" android:grantUriPermissions=\"true\" android:name=\"android.support.v4.content.FileProvider\"><meta-data android:name=\"android.support.FILE_PROVIDER_PATHS\" android:resource=\"@xml/provider_paths\" /></provider>",
              "count": 1
            },
            {
              "xml": "<meta-data android:name=\"com.facebook.sdk.ApplicationId\" android:value=\"@string/fb_app_id\" />",
              "count": 1
            },
            {
              "xml": "<meta-data android:name=\"com.facebook.sdk.ApplicationName\" android:value=\"@string/fb_app_name\" />",
              "count": 1
            },
            {
              "xml": "<activity android:configChanges=\"keyboard|keyboardHidden|screenLayout|screenSize|orientation\" android:label=\"@string/fb_app_name\" android:name=\"com.facebook.FacebookActivity\" />",
              "count": 1
            }
          ],
          "/manifest": [
            {
              "xml": "<uses-permission android:name=\"android.permission.VIBRATE\" />",
              "count": 1
            }
          ]
        }
      },
      "res/values/facebookconnect.xml": {
        "parents": {
          "/*": [
            {
              "xml": "<string name=\"fb_app_id\">296790334414922</string>",
              "count": 1
            },
            {
              "xml": "<string name=\"fb_app_name\">Chalkbord</string>",
              "count": 1
            }
          ]
        }
      },
      "config.xml": {
        "parents": {
          "/*": [
            {
              "xml": "<feature name=\"Keyboard\"><param name=\"android-package\" onload=\"true\" value=\"io.ionic.keyboard.IonicKeyboard\" /></feature>",
              "count": 1
            }
          ]
        }
      }
    }
  },
  "installed_plugins": {
    "cordova-plugin-actionsheet": {
      "PACKAGE_NAME": "locale.alpha"
    },
    "cordova-plugin-camera": {
      "PACKAGE_NAME": "locale.alpha"
    },
    "cordova-plugin-device": {
      "PACKAGE_NAME": "locale.alpha"
    },
    "cordova-plugin-dialogs": {
      "PACKAGE_NAME": "locale.alpha"
    },
    "cordova-plugin-facebook4": {
      "APP_ID": "296790334414922",
      "APP_NAME": "Chalkbord",
      "ANDROID_SDK_VERSION": "4.+",
      "PACKAGE_NAME": "locale.alpha"
    },
    "cordova-plugin-geolocation": {
      "PACKAGE_NAME": "locale.alpha"
    },
    "cordova-plugin-inappbrowser": {
      "PACKAGE_NAME": "locale.alpha"
    },
    "cordova-plugin-ionic-keyboard": {
      "PACKAGE_NAME": "locale.alpha"
    },
    "cordova-plugin-ionic-webview": {
      "PACKAGE_NAME": "locale.alpha"
    },
    "cordova-plugin-splashscreen": {
      "PACKAGE_NAME": "locale.alpha"
    },
    "cordova-plugin-statusbar": {
      "PACKAGE_NAME": "locale.alpha"
    },
    "cordova-plugin-uniquedeviceid": {
      "PACKAGE_NAME": "locale.alpha"
    },
    "cordova-plugin-velda-devicefeedback": {
      "PACKAGE_NAME": "locale.alpha"
    },
    "cordova-plugin-vibration": {
      "PACKAGE_NAME": "locale.alpha"
    },
    "cordova-plugin-whitelist": {
      "PACKAGE_NAME": "locale.alpha"
    },
    "cordova-sqlite-storage": {
      "PACKAGE_NAME": "locale.alpha"
    },
    "mx.ferreyra.callnumber": {
      "PACKAGE_NAME": "locale.alpha"
    },
    "uk.co.workingedge.phonegap.plugin.launchnavigator": {
      "PACKAGE_NAME": "locale.alpha"
    }
  },
  "dependent_plugins": {},
  "modules": [
    {
      "id": "cordova-plugin-actionsheet.ActionSheet",
      "file": "plugins/cordova-plugin-actionsheet/www/ActionSheet.js",
      "pluginId": "cordova-plugin-actionsheet",
      "clobbers": [
        "window.plugins.actionsheet"
      ]
    },
    {
      "id": "cordova-plugin-camera.Camera",
      "file": "plugins/cordova-plugin-camera/www/CameraConstants.js",
      "pluginId": "cordova-plugin-camera",
      "clobbers": [
        "Camera"
      ]
    },
    {
      "id": "cordova-plugin-camera.CameraPopoverOptions",
      "file": "plugins/cordova-plugin-camera/www/CameraPopoverOptions.js",
      "pluginId": "cordova-plugin-camera",
      "clobbers": [
        "CameraPopoverOptions"
      ]
    },
    {
      "id": "cordova-plugin-camera.camera",
      "file": "plugins/cordova-plugin-camera/www/Camera.js",
      "pluginId": "cordova-plugin-camera",
      "clobbers": [
        "navigator.camera"
      ]
    },
    {
      "id": "cordova-plugin-camera.CameraPopoverHandle",
      "file": "plugins/cordova-plugin-camera/www/CameraPopoverHandle.js",
      "pluginId": "cordova-plugin-camera",
      "clobbers": [
        "CameraPopoverHandle"
      ]
    },
    {
      "id": "cordova-plugin-device.device",
      "file": "plugins/cordova-plugin-device/www/device.js",
      "pluginId": "cordova-plugin-device",
      "clobbers": [
        "device"
      ]
    },
    {
      "id": "cordova-plugin-dialogs.notification",
      "file": "plugins/cordova-plugin-dialogs/www/notification.js",
      "pluginId": "cordova-plugin-dialogs",
      "merges": [
        "navigator.notification"
      ]
    },
    {
      "id": "cordova-plugin-dialogs.notification_android",
      "file": "plugins/cordova-plugin-dialogs/www/android/notification.js",
      "pluginId": "cordova-plugin-dialogs",
      "merges": [
        "navigator.notification"
      ]
    },
    {
      "id": "cordova-plugin-facebook4.FacebookConnectPlugin",
      "file": "plugins/cordova-plugin-facebook4/www/facebook-native.js",
      "pluginId": "cordova-plugin-facebook4",
      "clobbers": [
        "facebookConnectPlugin"
      ]
    },
    {
      "id": "cordova-plugin-geolocation.geolocation",
      "file": "plugins/cordova-plugin-geolocation/www/android/geolocation.js",
      "pluginId": "cordova-plugin-geolocation",
      "clobbers": [
        "navigator.geolocation"
      ]
    },
    {
      "id": "cordova-plugin-geolocation.PositionError",
      "file": "plugins/cordova-plugin-geolocation/www/PositionError.js",
      "pluginId": "cordova-plugin-geolocation",
      "runs": true
    },
    {
      "id": "cordova-plugin-inappbrowser.inappbrowser",
      "file": "plugins/cordova-plugin-inappbrowser/www/inappbrowser.js",
      "pluginId": "cordova-plugin-inappbrowser",
      "clobbers": [
        "cordova.InAppBrowser.open",
        "window.open"
      ]
    },
    {
      "id": "cordova-plugin-ionic-keyboard.keyboard",
      "file": "plugins/cordova-plugin-ionic-keyboard/www/android/keyboard.js",
      "pluginId": "cordova-plugin-ionic-keyboard",
      "clobbers": [
        "window.Keyboard"
      ]
    },
    {
      "id": "cordova-plugin-splashscreen.SplashScreen",
      "file": "plugins/cordova-plugin-splashscreen/www/splashscreen.js",
      "pluginId": "cordova-plugin-splashscreen",
      "clobbers": [
        "navigator.splashscreen"
      ]
    },
    {
      "id": "cordova-plugin-statusbar.statusbar",
      "file": "plugins/cordova-plugin-statusbar/www/statusbar.js",
      "pluginId": "cordova-plugin-statusbar",
      "clobbers": [
        "window.StatusBar"
      ]
    },
    {
      "id": "cordova-plugin-uniquedeviceid.UniqueDeviceID",
      "file": "plugins/cordova-plugin-uniquedeviceid/www/uniqueid.js",
      "pluginId": "cordova-plugin-uniquedeviceid",
      "merges": [
        "window.plugins.uniqueDeviceID"
      ]
    },
    {
      "id": "cordova-plugin-velda-devicefeedback.DeviceFeedback",
      "file": "plugins/cordova-plugin-velda-devicefeedback/DeviceFeedback.js",
      "pluginId": "cordova-plugin-velda-devicefeedback",
      "clobbers": [
        "window.plugins.deviceFeedback"
      ]
    },
    {
      "id": "cordova-sqlite-storage.SQLitePlugin",
      "file": "plugins/cordova-sqlite-storage/www/SQLitePlugin.js",
      "pluginId": "cordova-sqlite-storage",
      "clobbers": [
        "SQLitePlugin"
      ]
    },
    {
      "id": "mx.ferreyra.callnumber.CallNumber",
      "file": "plugins/mx.ferreyra.callnumber/www/CallNumber.js",
      "pluginId": "mx.ferreyra.callnumber",
      "clobbers": [
        "call"
      ]
    },
    {
      "id": "uk.co.workingedge.phonegap.plugin.launchnavigator.Common",
      "file": "plugins/uk.co.workingedge.phonegap.plugin.launchnavigator/www/common.js",
      "pluginId": "uk.co.workingedge.phonegap.plugin.launchnavigator",
      "clobbers": [
        "launchnavigator"
      ]
    },
    {
      "id": "uk.co.workingedge.phonegap.plugin.launchnavigator.LocalForage",
      "file": "plugins/uk.co.workingedge.phonegap.plugin.launchnavigator/www/localforage.v1.5.0.min.js",
      "pluginId": "uk.co.workingedge.phonegap.plugin.launchnavigator",
      "clobbers": [
        "localforage"
      ]
    },
    {
      "id": "uk.co.workingedge.phonegap.plugin.launchnavigator.LaunchNavigator",
      "file": "plugins/uk.co.workingedge.phonegap.plugin.launchnavigator/www/android/launchnavigator.js",
      "pluginId": "uk.co.workingedge.phonegap.plugin.launchnavigator",
      "merges": [
        "launchnavigator"
      ]
    }
  ],
  "plugin_metadata": {
    "cordova-plugin-actionsheet": "2.3.3",
    "cordova-plugin-camera": "4.0.2",
    "cordova-plugin-device": "1.1.7",
    "cordova-plugin-dialogs": "2.0.1",
    "cordova-plugin-facebook4": "2.2.0",
    "cordova-plugin-geolocation": "4.0.1",
    "cordova-plugin-inappbrowser": "1.7.2",
    "cordova-plugin-ionic-keyboard": "2.0.5",
    "cordova-plugin-ionic-webview": "1.1.16",
    "cordova-plugin-splashscreen": "4.1.0",
    "cordova-plugin-statusbar": "2.4.1",
    "cordova-plugin-uniquedeviceid": "1.3.2",
    "cordova-plugin-velda-devicefeedback": "0.0.2",
    "cordova-plugin-vibration": "3.1.0",
    "cordova-plugin-whitelist": "1.3.3",
    "cordova-sqlite-storage": "2.3.1",
    "mx.ferreyra.callnumber": "0.0.2",
    "uk.co.workingedge.phonegap.plugin.launchnavigator": "4.1.3"
  }
}